{
  "id": "case_254",
  "summary": "1. N Engl J Med. 2010 Jul 22;363(4):373-81. doi: 10.1056/NEJMcpc1004364.",
  "steps": [
    {
      "id": 1,
      "text": "1. N Engl J Med. 2010 Jul 22;363(4):373-81. doi: 10.1056/NEJMcpc1004364."
    },
    {
      "id": 2,
      "text": "Case records of the Massachusetts General Hospital. Case 22-2010. An 87-year-old \nwoman with dementia and a seizure."
    },
    {
      "id": 3,
      "text": "Greenberg SM(1), Rapalino O, Frosch MP."
    },
    {
      "id": 4,
      "text": "Author information:\n(1)Department of Neurology, Massachusetts General Hospital, Boston, USA."
    },
    {
      "id": 5,
      "text": "DOI: 10.1056/NEJMcpc1004364\nPMID: 20660406 [Indexed for MEDLINE]"
    }
  ]
}
