{
  "id": "case_055",
  "summary": "1. N Engl J Med. 2015 Jul 16;373(3):263-71. doi: 10.1056/NEJMcpc1501310.",
  "steps": [
    {
      "id": 1,
      "text": "1. N Engl J Med. 2015 Jul 16;373(3):263-71. doi: 10.1056/NEJMcpc1501310."
    },
    {
      "id": 2,
      "text": "CASE RECORDS of the MASSACHUSETTS GENERAL HOSPITAL. Case 22-2015. A 20-Year-Old \nMan with Sore Throat, Fever, Myalgias, and a Pericardial Effusion."
    },
    {
      "id": 3,
      "text": "Hunt DP, Scheske JA, Dudzinski DM, Arvikar SL."
    },
    {
      "id": 4,
      "text": "DOI: 10.1056/NEJMcpc1501310\nPMID: 26176384 [Indexed for MEDLINE]"
    }
  ]
}
